tapqir/__init__.py
tapqir/_version.py
tapqir/app.ipynb
tapqir/exceptions.py
tapqir/gui.py
tapqir/handlers.py
tapqir/logger.py
tapqir/main.py
tapqir/distributions/__init__.py
tapqir/distributions/affine_beta.py
tapqir/distributions/ksmogn.py
tapqir/distributions/util.py
tapqir/imscroll/__init__.py
tapqir/imscroll/glimpse_reader.py
tapqir/infer/__init__.py
tapqir/infer/elbo.py
tapqir/infer/sum_product.py
tapqir/models/__init__.py
tapqir/models/cosmos.py
tapqir/models/crosstalk.py
tapqir/models/hmm.py
tapqir/models/model.py
tapqir/utils/__init__.py
tapqir/utils/dataset.py
tapqir/utils/imscroll.py
tapqir/utils/mle_analysis.py
tapqir/utils/simulate.py
tapqir/utils/stats.py
test/__init__.py
test/test_imscroll.py
test/test_tapqir.py
tapqir-1.1.19.dist-info/LICENSE.md
tapqir-1.1.19.dist-info/METADATA
tapqir-1.1.19.dist-info/WHEEL
tapqir-1.1.19.dist-info/entry_points.txt
tapqir-1.1.19.dist-info/top_level.txt
tapqir-1.1.19.dist-info/RECORD
