Metadata-Version: 2.1
Name: tapqir
Version: 1.1.19
Summary: Bayesian analysis of co-localization single-molecule microscopy image data
Home-page: https://tapqir.readthedocs.io
Author: Yerdos Ordabayev
Author-email: ordabayev@brandeis.edu
License: Apache 2.0
Project-URL: Documentation, https://tapqir.readthedocs.io
Project-URL: Source, https://github.com/gelles-brandeis/tapqir
Keywords: image-classification probabilistic-programming cosmos pyro
Platform: UNKNOWN
Classifier: Intended Audience :: Developers
Classifier: Intended Audience :: Science/Research
Classifier: License :: OSI Approved :: Apache Software License
Classifier: Operating System :: OS Independent
Classifier: Programming Language :: Python :: 3
Requires-Python: >=3.7
Requires-Dist: colorama
Requires-Dist: funsor (>=0.4.4)
Requires-Dist: future
Requires-Dist: ipyevents
Requires-Dist: ipyfilechooser
Requires-Dist: ipympl
Requires-Dist: ipywidgets
Requires-Dist: matplotlib (>=3.5.3)
Requires-Dist: pandas
Requires-Dist: protobuf (<3.20,>=3.9)
Requires-Dist: pykeops (>=2.0)
Requires-Dist: pyro-ppl (>=1.8.5)
Requires-Dist: pyyaml (>=6.0)
Requires-Dist: scikit-learn
Requires-Dist: scipy
Requires-Dist: tensorboard
Requires-Dist: torch (>=2.0.1)
Requires-Dist: typer
Provides-Extra: desktop
Requires-Dist: voila ; extra == 'desktop'
Provides-Extra: dev
Requires-Dist: voila ; extra == 'dev'
Requires-Dist: notebook ; extra == 'dev'
Requires-Dist: black[jupyter] ; extra == 'dev'
Requires-Dist: flake8 ; extra == 'dev'
Requires-Dist: isort ; extra == 'dev'
Requires-Dist: pytest ; extra == 'dev'
Requires-Dist: pytest-xvfb ; extra == 'dev'
Requires-Dist: IPython ; extra == 'dev'
Requires-Dist: nbsphinx (>=0.8.5) ; extra == 'dev'
Requires-Dist: pydata-sphinx-theme ; extra == 'dev'
Requires-Dist: sphinx ; extra == 'dev'
Requires-Dist: sphinx-autodoc-typehints ; extra == 'dev'
Requires-Dist: sphinx-click ; extra == 'dev'
Requires-Dist: sphinx-copybutton ; extra == 'dev'
Requires-Dist: sphinx-gallery ; extra == 'dev'
Requires-Dist: sphinx-panels ; extra == 'dev'
Provides-Extra: docs
Requires-Dist: IPython ; extra == 'docs'
Requires-Dist: nbsphinx (>=0.8.5) ; extra == 'docs'
Requires-Dist: pydata-sphinx-theme ; extra == 'docs'
Requires-Dist: sphinx ; extra == 'docs'
Requires-Dist: sphinx-autodoc-typehints ; extra == 'docs'
Requires-Dist: sphinx-click ; extra == 'docs'
Requires-Dist: sphinx-copybutton ; extra == 'docs'
Requires-Dist: sphinx-gallery ; extra == 'docs'
Requires-Dist: sphinx-panels ; extra == 'docs'
Provides-Extra: extras
Requires-Dist: notebook ; extra == 'extras'
Provides-Extra: test
Requires-Dist: notebook ; extra == 'test'
Requires-Dist: black[jupyter] ; extra == 'test'
Requires-Dist: flake8 ; extra == 'test'
Requires-Dist: isort ; extra == 'test'
Requires-Dist: pytest ; extra == 'test'
Requires-Dist: pytest-xvfb ; extra == 'test'
